LICENSE.txt
MANIFEST.in
README.md
setup.cfg
setup.py
letsencrypt_proxmox.egg-info/PKG-INFO
letsencrypt_proxmox.egg-info/SOURCES.txt
letsencrypt_proxmox.egg-info/dependency_links.txt
letsencrypt_proxmox.egg-info/entry_points.txt
letsencrypt_proxmox.egg-info/requires.txt
letsencrypt_proxmox.egg-info/top_level.txt
proxmox_plugin/__init__.py
proxmox_plugin/proxmox.py