Metadata-Version: 1.1
Name: letsencrypt-proxmox
Version: 0.1.0
Summary: Proxmox VE plugin for Let's Encrypt client
Home-page: https://github.com/kharkevich/letsencrypt-proxmox
Author: Aliaksandr Kharkevich
Author-email: aliaksandr_kharkevich@outlook.com
License: Apache License 2.0
Download-URL: https://github.com/kharkevich/letsencrypt-proxmox/archive/0.1.0.tar.gz
Keywords: letsencrypt,proxmox
Platform: any
Classifier: Development Status :: 3 - Alpha
Classifier: Topic :: Utilities
Classifier: License :: OSI Approved :: Apache Software License
